LICENSE
MANIFEST.in
README.md
README.rst
setup.py
numpy_linreg/__init__.py
numpy_linreg/metrics.py
numpy_linreg/ols.py
numpy_linreg/ridge.py
numpy_linreg/utils.py
numpy_linreg.egg-info/PKG-INFO
numpy_linreg.egg-info/SOURCES.txt
numpy_linreg.egg-info/dependency_links.txt
numpy_linreg.egg-info/requires.txt
numpy_linreg.egg-info/top_level.txt
numpy_linreg.egg-info/zip-safe