Metadata-Version: 1.2
Name: numpy-linreg
Version: 0.1.2
Summary: Linear Regression with numpy only.
Home-page: http://github.com/ulf1/numpy-linreg
Author: Ulf Hamster
Author-email: 554c46@gmail.com
License: Apache License 2.0
Platform: UNKNOWN
Requires-Python: >=3.6
